quantastor/__init__.py
quantastor/qs_client.py
quantastor_qsclient-6.2.1.data/scripts/qs_client.py
quantastor_qsclient-6.2.1.dist-info/LICENSE
quantastor_qsclient-6.2.1.dist-info/METADATA
quantastor_qsclient-6.2.1.dist-info/WHEEL
quantastor_qsclient-6.2.1.dist-info/top_level.txt
quantastor_qsclient-6.2.1.dist-info/RECORD
